address_hammer/__address__.py
address_hammer/__data__.py
address_hammer/__fuzzy_string__.py
address_hammer/__hammer__.py
address_hammer/__init__.py
address_hammer/__parsing__.py
address_hammer/__regex__.py
address_hammer/__sheet__.py
address_hammer/__types__.py
address_hammer/__zipper__.py
address_hammer/test.py
address_hammer-0.1.1.dist-info/LICENSE
address_hammer-0.1.1.dist-info/METADATA
address_hammer-0.1.1.dist-info/WHEEL
address_hammer-0.1.1.dist-info/top_level.txt
address_hammer-0.1.1.dist-info/RECORD
