Metadata-Version: 2.1
Name: address-hammer
Version: 0.1.1
Summary: Tool for processing U.S residential addresses
Home-page: https://github.com/Lambda-Logan/address_hammer
Author: Logan Dimond
Author-email: lambda.dimond@gmail.com
License: MPL-2.0
Platform: UNKNOWN
License-File: LICENSE
